{
	"pattrstorage" : 	{
		"name" : "seqX",
		"slots" : 		{
			"1" : 			{
				"id" : 1,
				"data" : 				{
					"decay" : [ 0.186588921282799 ],
					"filterFreq" : [ 0.428571428571429 ],
					"fuzz" : [ 0.285714285714286 ],
					"noise" : [ 0.0 ],
					"octave" : [ 3 ],
					"panning" : [ 0.500028766209069 ],
					"reverb" : [ 0.571428571428571 ],
					"subdivide" : [ 2 ],
					"poly~.1::MLE.seq::enable" : [ 3, 8, 1, 0, 8, 0, 1000, 2000, 3000, 4000, 5000, 6000, 7000, 2, 2, 2, 2, 2, 2, 2, 2 ],
					"poly~.1::MLE.seq::hitProb" : [ 127, 127, 127, 127, 127, 127, 127, 127 ],
					"poly~.1::MLE.seq::seq" : [ 0, 2, 0, 1, 3, 2, 2, 1 ],
					"poly~.1::MLE.dist::FB1gain" : [ 0 ],
					"poly~.1::MLE.dist::FB2_gain" : [ 63 ],
					"poly~.1::MLE.dist::FB2samples" : [ 30 ],
					"poly~.1::MLE.dist::Gain" : [ 39 ],
					"poly~.1::MLE.dist::LPF_freq" : [ 190.0 ],
					"poly~.1::MLE.dist::LPF_gain" : [ 1.152208752109341 ],
					"poly~.1::MLE.dist::MIX" : [ 10 ],
					"poly~.1::MLE.dist::PHPF_freq" : [ 880.0 ],
					"poly~.1::MLE.dist::PHPF_gain" : [ 0.9208984375 ],
					"poly~.1::MLE.dist::bias" : [ 23 ],
					"poly~.1::MLE.dist::dynamics" : [ 127 ],
					"poly~.1::MLE.dist::tone" : [ 46 ],
					"poly~.1::MLE.dist::volume" : [ 93 ],
					"poly~.2::MLE.seq::enable" : [ 3, 8, 1, 0, 8, 0, 1000, 2000, 3000, 4000, 5000, 6000, 7000, 2, 2, 2, 2, 2, 2, 2, 2 ],
					"poly~.2::MLE.seq::hitProb" : [ 127, 127, 127, 127, 127, 127, 127, 127 ],
					"poly~.2::MLE.seq::seq" : [ 7, 0, 0, 0, 0, 0, 0, 0 ],
					"poly~.2::MLE.dist::FB1gain" : [ 0 ],
					"poly~.2::MLE.dist::FB2_gain" : [ 63 ],
					"poly~.2::MLE.dist::FB2samples" : [ 30 ],
					"poly~.2::MLE.dist::Gain" : [ 26 ],
					"poly~.2::MLE.dist::LPF_freq" : [ 190.0 ],
					"poly~.2::MLE.dist::LPF_gain" : [ 1.152208752109341 ],
					"poly~.2::MLE.dist::MIX" : [ 127 ],
					"poly~.2::MLE.dist::PHPF_freq" : [ 880.0 ],
					"poly~.2::MLE.dist::PHPF_gain" : [ 0.9208984375 ],
					"poly~.2::MLE.dist::bias" : [ 23 ],
					"poly~.2::MLE.dist::dynamics" : [ 127 ],
					"poly~.2::MLE.dist::tone" : [ 46 ],
					"poly~.2::MLE.dist::volume" : [ 24 ],
					"poly~.3::MLE.seq::enable" : [ 3, 8, 1, 0, 8, 0, 1000, 2000, 3000, 4000, 5000, 6000, 7000, 2, 2, 2, 2, 2, 2, 2, 2 ],
					"poly~.3::MLE.seq::hitProb" : [ 127, 127, 127, 127, 127, 127, 127, 127 ],
					"poly~.3::MLE.seq::seq" : [ 7, 0, 0, 0, 0, 0, 0, 0 ],
					"poly~.3::MLE.dist::FB1gain" : [ 0 ],
					"poly~.3::MLE.dist::FB2_gain" : [ 63 ],
					"poly~.3::MLE.dist::FB2samples" : [ 30 ],
					"poly~.3::MLE.dist::Gain" : [ 26 ],
					"poly~.3::MLE.dist::LPF_freq" : [ 190.0 ],
					"poly~.3::MLE.dist::LPF_gain" : [ 1.152208752109341 ],
					"poly~.3::MLE.dist::MIX" : [ 127 ],
					"poly~.3::MLE.dist::PHPF_freq" : [ 880.0 ],
					"poly~.3::MLE.dist::PHPF_gain" : [ 0.9208984375 ],
					"poly~.3::MLE.dist::bias" : [ 23 ],
					"poly~.3::MLE.dist::dynamics" : [ 127 ],
					"poly~.3::MLE.dist::tone" : [ 46 ],
					"poly~.3::MLE.dist::volume" : [ 24 ],
					"poly~.4::MLE.seq::enable" : [ 3, 8, 1, 0, 8, 0, 1000, 2000, 3000, 4000, 5000, 6000, 7000, 2, 2, 2, 2, 2, 2, 2, 2 ],
					"poly~.4::MLE.seq::hitProb" : [ 127, 127, 127, 127, 127, 127, 127, 127 ],
					"poly~.4::MLE.seq::seq" : [ 7, 0, 0, 0, 0, 0, 0, 0 ],
					"poly~.4::MLE.dist::FB1gain" : [ 0 ],
					"poly~.4::MLE.dist::FB2_gain" : [ 63 ],
					"poly~.4::MLE.dist::FB2samples" : [ 30 ],
					"poly~.4::MLE.dist::Gain" : [ 26 ],
					"poly~.4::MLE.dist::LPF_freq" : [ 190.0 ],
					"poly~.4::MLE.dist::LPF_gain" : [ 1.152208752109341 ],
					"poly~.4::MLE.dist::MIX" : [ 127 ],
					"poly~.4::MLE.dist::PHPF_freq" : [ 880.0 ],
					"poly~.4::MLE.dist::PHPF_gain" : [ 0.9208984375 ],
					"poly~.4::MLE.dist::bias" : [ 23 ],
					"poly~.4::MLE.dist::dynamics" : [ 127 ],
					"poly~.4::MLE.dist::tone" : [ 46 ],
					"poly~.4::MLE.dist::volume" : [ 24 ],
					"poly~.5::MLE.seq::enable" : [ 3, 8, 1, 0, 8, 0, 1000, 2000, 3000, 4000, 5000, 6000, 7000, 2, 2, 2, 2, 2, 2, 2, 2 ],
					"poly~.5::MLE.seq::hitProb" : [ 127, 127, 127, 127, 127, 127, 127, 127 ],
					"poly~.5::MLE.seq::seq" : [ 7, 0, 0, 0, 0, 0, 0, 0 ],
					"poly~.5::MLE.dist::FB1gain" : [ 0 ],
					"poly~.5::MLE.dist::FB2_gain" : [ 63 ],
					"poly~.5::MLE.dist::FB2samples" : [ 30 ],
					"poly~.5::MLE.dist::Gain" : [ 26 ],
					"poly~.5::MLE.dist::LPF_freq" : [ 190.0 ],
					"poly~.5::MLE.dist::LPF_gain" : [ 1.152208752109341 ],
					"poly~.5::MLE.dist::MIX" : [ 127 ],
					"poly~.5::MLE.dist::PHPF_freq" : [ 880.0 ],
					"poly~.5::MLE.dist::PHPF_gain" : [ 0.9208984375 ],
					"poly~.5::MLE.dist::bias" : [ 23 ],
					"poly~.5::MLE.dist::dynamics" : [ 127 ],
					"poly~.5::MLE.dist::tone" : [ 46 ],
					"poly~.5::MLE.dist::volume" : [ 24 ],
					"poly~.6::MLE.seq::enable" : [ 3, 8, 1, 0, 8, 0, 1000, 2000, 3000, 4000, 5000, 6000, 7000, 2, 2, 2, 2, 2, 2, 2, 2 ],
					"poly~.6::MLE.seq::hitProb" : [ 127, 127, 127, 127, 127, 127, 127, 127 ],
					"poly~.6::MLE.seq::seq" : [ 7, 0, 0, 0, 0, 0, 0, 0 ],
					"poly~.6::MLE.dist::FB1gain" : [ 0 ],
					"poly~.6::MLE.dist::FB2_gain" : [ 63 ],
					"poly~.6::MLE.dist::FB2samples" : [ 30 ],
					"poly~.6::MLE.dist::Gain" : [ 26 ],
					"poly~.6::MLE.dist::LPF_freq" : [ 190.0 ],
					"poly~.6::MLE.dist::LPF_gain" : [ 1.152208752109341 ],
					"poly~.6::MLE.dist::MIX" : [ 127 ],
					"poly~.6::MLE.dist::PHPF_freq" : [ 880.0 ],
					"poly~.6::MLE.dist::PHPF_gain" : [ 0.9208984375 ],
					"poly~.6::MLE.dist::bias" : [ 23 ],
					"poly~.6::MLE.dist::dynamics" : [ 127 ],
					"poly~.6::MLE.dist::tone" : [ 46 ],
					"poly~.6::MLE.dist::volume" : [ 24 ],
					"poly~.7::MLE.seq::enable" : [ 3, 8, 1, 0, 8, 0, 1000, 2000, 3000, 4000, 5000, 6000, 7000, 2, 2, 2, 2, 2, 2, 2, 2 ],
					"poly~.7::MLE.seq::hitProb" : [ 127, 127, 127, 127, 127, 127, 127, 127 ],
					"poly~.7::MLE.seq::seq" : [ 7, 0, 0, 0, 0, 0, 0, 0 ],
					"poly~.7::MLE.dist::FB1gain" : [ 0 ],
					"poly~.7::MLE.dist::FB2_gain" : [ 63 ],
					"poly~.7::MLE.dist::FB2samples" : [ 30 ],
					"poly~.7::MLE.dist::Gain" : [ 26 ],
					"poly~.7::MLE.dist::LPF_freq" : [ 190.0 ],
					"poly~.7::MLE.dist::LPF_gain" : [ 1.152208752109341 ],
					"poly~.7::MLE.dist::MIX" : [ 127 ],
					"poly~.7::MLE.dist::PHPF_freq" : [ 880.0 ],
					"poly~.7::MLE.dist::PHPF_gain" : [ 0.9208984375 ],
					"poly~.7::MLE.dist::bias" : [ 23 ],
					"poly~.7::MLE.dist::dynamics" : [ 127 ],
					"poly~.7::MLE.dist::tone" : [ 46 ],
					"poly~.7::MLE.dist::volume" : [ 24 ],
					"poly~.8::MLE.seq::enable" : [ 3, 8, 1, 0, 8, 0, 1000, 2000, 3000, 4000, 5000, 6000, 7000, 2, 2, 2, 2, 2, 2, 2, 2 ],
					"poly~.8::MLE.seq::hitProb" : [ 127, 127, 127, 127, 127, 127, 127, 127 ],
					"poly~.8::MLE.seq::seq" : [ 7, 0, 0, 0, 0, 0, 0, 0 ],
					"poly~.8::MLE.dist::FB1gain" : [ 0 ],
					"poly~.8::MLE.dist::FB2_gain" : [ 63 ],
					"poly~.8::MLE.dist::FB2samples" : [ 30 ],
					"poly~.8::MLE.dist::Gain" : [ 26 ],
					"poly~.8::MLE.dist::LPF_freq" : [ 190.0 ],
					"poly~.8::MLE.dist::LPF_gain" : [ 1.152208752109341 ],
					"poly~.8::MLE.dist::MIX" : [ 127 ],
					"poly~.8::MLE.dist::PHPF_freq" : [ 880.0 ],
					"poly~.8::MLE.dist::PHPF_gain" : [ 0.9208984375 ],
					"poly~.8::MLE.dist::bias" : [ 23 ],
					"poly~.8::MLE.dist::dynamics" : [ 127 ],
					"poly~.8::MLE.dist::tone" : [ 46 ],
					"poly~.8::MLE.dist::volume" : [ 24 ],
					"MLE.seq[1]::enable" : [ 3, 8, 1, 0, 8, 0, 1000, 2000, 3000, 4000, 5000, 6000, 7000, 2, 2, 2, 2, 2, 2, 2, 2 ],
					"MLE.seq[1]::hitProb" : [ 127, 127, 127, 127, 127, 127, 127, 127 ],
					"MLE.seq[1]::seq" : [ 7, 0, 0, 0, 0, 0, 0, 0 ],
					"MLE.seq[2]::enable" : [ 3, 8, 1, 0, 8, 0, 1000, 2000, 3000, 4000, 5000, 6000, 7000, 2, 2, 2, 2, 2, 2, 2, 2 ],
					"MLE.seq[2]::hitProb" : [ 127, 127, 127, 127, 127, 127, 127, 127 ],
					"MLE.seq[2]::seq" : [ 0, 2, 0, 1, 3, 2, 2, 1 ],
					"MLE.seq[4]::enable" : [ 3, 8, 1, 0, 8, 0, 1000, 2000, 3000, 4000, 5000, 6000, 7000, 2, 2, 2, 2, 2, 2, 2, 2 ],
					"MLE.seq[4]::hitProb" : [ 127, 127, 127, 127, 127, 127, 127, 127 ],
					"MLE.seq[4]::seq" : [ 7, 0, 0, 0, 0, 0, 0, 0 ],
					"MLE.seq[3]::enable" : [ 3, 8, 1, 0, 8, 0, 1000, 2000, 3000, 4000, 5000, 6000, 7000, 2, 2, 2, 2, 2, 2, 2, 2 ],
					"MLE.seq[3]::hitProb" : [ 127, 127, 127, 127, 127, 127, 127, 127 ],
					"MLE.seq[3]::seq" : [ 7, 0, 0, 0, 0, 0, 0, 0 ],
					"MLE.seq[8]::enable" : [ 3, 8, 1, 0, 8, 0, 1000, 2000, 3000, 4000, 5000, 6000, 7000, 2, 2, 2, 2, 2, 2, 2, 2 ],
					"MLE.seq[8]::hitProb" : [ 127, 127, 127, 127, 127, 127, 127, 127 ],
					"MLE.seq[8]::seq" : [ 7, 0, 0, 0, 0, 0, 0, 0 ],
					"MLE.seq[7]::enable" : [ 3, 8, 1, 0, 8, 0, 1000, 2000, 3000, 4000, 5000, 6000, 7000, 2, 2, 2, 2, 2, 2, 2, 2 ],
					"MLE.seq[7]::hitProb" : [ 127, 127, 127, 127, 127, 127, 127, 127 ],
					"MLE.seq[7]::seq" : [ 7, 0, 0, 0, 0, 0, 0, 0 ],
					"MLE.seq[6]::enable" : [ 3, 8, 1, 0, 8, 0, 1000, 2000, 3000, 4000, 5000, 6000, 7000, 2, 2, 2, 2, 2, 2, 2, 2 ],
					"MLE.seq[6]::hitProb" : [ 127, 127, 127, 127, 127, 127, 127, 127 ],
					"MLE.seq[6]::seq" : [ 7, 0, 0, 0, 0, 0, 0, 0 ],
					"MLE.seq::enable" : [ 3, 8, 1, 0, 8, 0, 1000, 2000, 3000, 4000, 5000, 6000, 7000, 2, 2, 2, 2, 2, 2, 2, 2 ],
					"MLE.seq::hitProb" : [ 127, 127, 127, 127, 127, 127, 127, 127 ],
					"MLE.seq::seq" : [ 0, 2, 0, 1, 3, 2, 2, 1 ]
				}

			}
,
			"2" : 			{
				"id" : 2,
				"data" : 				{
					"decay" : [ 0.261588921282799 ],
					"filterFreq" : [ 0.353571428571429 ],
					"fuzz" : [ 0.285714285714286 ],
					"noise" : [ 0.275 ],
					"octave" : [ 3 ],
					"panning" : [ 0.50002876620907 ],
					"reverb" : [ 0.146428571428571 ],
					"subdivide" : [ 4 ],
					"poly~.1::MLE.seq::enable" : [ 3, 8, 1, 0, 8, 0, 1000, 2000, 3000, 4000, 5000, 6000, 7000, 2, 2, 2, 2, 2, 2, 2, 2 ],
					"poly~.1::MLE.seq::hitProb" : [ 127, 127, 127, 127, 127, 127, 127, 127 ],
					"poly~.1::MLE.seq::seq" : [ 6, 6, 6, 5, 4, 3, 1, 0 ],
					"poly~.1::MLE.dist::FB1gain" : [ 0 ],
					"poly~.1::MLE.dist::FB2_gain" : [ 63 ],
					"poly~.1::MLE.dist::FB2samples" : [ 30 ],
					"poly~.1::MLE.dist::Gain" : [ 39 ],
					"poly~.1::MLE.dist::LPF_freq" : [ 190.0 ],
					"poly~.1::MLE.dist::LPF_gain" : [ 1.152208752109341 ],
					"poly~.1::MLE.dist::MIX" : [ 10 ],
					"poly~.1::MLE.dist::PHPF_freq" : [ 880.0 ],
					"poly~.1::MLE.dist::PHPF_gain" : [ 0.9208984375 ],
					"poly~.1::MLE.dist::bias" : [ 23 ],
					"poly~.1::MLE.dist::dynamics" : [ 127 ],
					"poly~.1::MLE.dist::tone" : [ 46 ],
					"poly~.1::MLE.dist::volume" : [ 93 ],
					"poly~.2::MLE.seq::enable" : [ 3, 8, 1, 0, 8, 0, 1000, 2000, 3000, 4000, 5000, 6000, 7000, 2, 2, 2, 2, 2, 2, 2, 2 ],
					"poly~.2::MLE.seq::hitProb" : [ 127, 127, 127, 127, 127, 127, 127, 127 ],
					"poly~.2::MLE.seq::seq" : [ 7, 0, 0, 0, 0, 0, 0, 0 ],
					"poly~.2::MLE.dist::FB1gain" : [ 0 ],
					"poly~.2::MLE.dist::FB2_gain" : [ 63 ],
					"poly~.2::MLE.dist::FB2samples" : [ 30 ],
					"poly~.2::MLE.dist::Gain" : [ 26 ],
					"poly~.2::MLE.dist::LPF_freq" : [ 190.0 ],
					"poly~.2::MLE.dist::LPF_gain" : [ 1.152208752109341 ],
					"poly~.2::MLE.dist::MIX" : [ 127 ],
					"poly~.2::MLE.dist::PHPF_freq" : [ 880.0 ],
					"poly~.2::MLE.dist::PHPF_gain" : [ 0.9208984375 ],
					"poly~.2::MLE.dist::bias" : [ 23 ],
					"poly~.2::MLE.dist::dynamics" : [ 127 ],
					"poly~.2::MLE.dist::tone" : [ 46 ],
					"poly~.2::MLE.dist::volume" : [ 24 ],
					"poly~.3::MLE.seq::enable" : [ 3, 8, 1, 0, 8, 0, 1000, 2000, 3000, 4000, 5000, 6000, 7000, 2, 2, 2, 2, 2, 2, 2, 2 ],
					"poly~.3::MLE.seq::hitProb" : [ 127, 127, 127, 127, 127, 127, 127, 127 ],
					"poly~.3::MLE.seq::seq" : [ 7, 0, 0, 0, 0, 0, 0, 0 ],
					"poly~.3::MLE.dist::FB1gain" : [ 0 ],
					"poly~.3::MLE.dist::FB2_gain" : [ 63 ],
					"poly~.3::MLE.dist::FB2samples" : [ 30 ],
					"poly~.3::MLE.dist::Gain" : [ 26 ],
					"poly~.3::MLE.dist::LPF_freq" : [ 190.0 ],
					"poly~.3::MLE.dist::LPF_gain" : [ 1.152208752109341 ],
					"poly~.3::MLE.dist::MIX" : [ 127 ],
					"poly~.3::MLE.dist::PHPF_freq" : [ 880.0 ],
					"poly~.3::MLE.dist::PHPF_gain" : [ 0.9208984375 ],
					"poly~.3::MLE.dist::bias" : [ 23 ],
					"poly~.3::MLE.dist::dynamics" : [ 127 ],
					"poly~.3::MLE.dist::tone" : [ 46 ],
					"poly~.3::MLE.dist::volume" : [ 24 ],
					"poly~.4::MLE.seq::enable" : [ 3, 8, 1, 0, 8, 0, 1000, 2000, 3000, 4000, 5000, 6000, 7000, 2, 2, 2, 2, 2, 2, 2, 2 ],
					"poly~.4::MLE.seq::hitProb" : [ 127, 127, 127, 127, 127, 127, 127, 127 ],
					"poly~.4::MLE.seq::seq" : [ 7, 0, 0, 0, 0, 0, 0, 0 ],
					"poly~.4::MLE.dist::FB1gain" : [ 0 ],
					"poly~.4::MLE.dist::FB2_gain" : [ 63 ],
					"poly~.4::MLE.dist::FB2samples" : [ 30 ],
					"poly~.4::MLE.dist::Gain" : [ 26 ],
					"poly~.4::MLE.dist::LPF_freq" : [ 190.0 ],
					"poly~.4::MLE.dist::LPF_gain" : [ 1.152208752109341 ],
					"poly~.4::MLE.dist::MIX" : [ 127 ],
					"poly~.4::MLE.dist::PHPF_freq" : [ 880.0 ],
					"poly~.4::MLE.dist::PHPF_gain" : [ 0.9208984375 ],
					"poly~.4::MLE.dist::bias" : [ 23 ],
					"poly~.4::MLE.dist::dynamics" : [ 127 ],
					"poly~.4::MLE.dist::tone" : [ 46 ],
					"poly~.4::MLE.dist::volume" : [ 24 ],
					"poly~.5::MLE.seq::enable" : [ 3, 8, 1, 0, 8, 0, 1000, 2000, 3000, 4000, 5000, 6000, 7000, 2, 2, 2, 2, 2, 2, 2, 2 ],
					"poly~.5::MLE.seq::hitProb" : [ 127, 127, 127, 127, 127, 127, 127, 127 ],
					"poly~.5::MLE.seq::seq" : [ 7, 0, 0, 0, 0, 0, 0, 0 ],
					"poly~.5::MLE.dist::FB1gain" : [ 0 ],
					"poly~.5::MLE.dist::FB2_gain" : [ 63 ],
					"poly~.5::MLE.dist::FB2samples" : [ 30 ],
					"poly~.5::MLE.dist::Gain" : [ 26 ],
					"poly~.5::MLE.dist::LPF_freq" : [ 190.0 ],
					"poly~.5::MLE.dist::LPF_gain" : [ 1.152208752109341 ],
					"poly~.5::MLE.dist::MIX" : [ 127 ],
					"poly~.5::MLE.dist::PHPF_freq" : [ 880.0 ],
					"poly~.5::MLE.dist::PHPF_gain" : [ 0.9208984375 ],
					"poly~.5::MLE.dist::bias" : [ 23 ],
					"poly~.5::MLE.dist::dynamics" : [ 127 ],
					"poly~.5::MLE.dist::tone" : [ 46 ],
					"poly~.5::MLE.dist::volume" : [ 24 ],
					"poly~.6::MLE.seq::enable" : [ 3, 8, 1, 0, 8, 0, 1000, 2000, 3000, 4000, 5000, 6000, 7000, 2, 2, 2, 2, 2, 2, 2, 2 ],
					"poly~.6::MLE.seq::hitProb" : [ 127, 127, 127, 127, 127, 127, 127, 127 ],
					"poly~.6::MLE.seq::seq" : [ 7, 0, 0, 0, 0, 0, 0, 0 ],
					"poly~.6::MLE.dist::FB1gain" : [ 0 ],
					"poly~.6::MLE.dist::FB2_gain" : [ 63 ],
					"poly~.6::MLE.dist::FB2samples" : [ 30 ],
					"poly~.6::MLE.dist::Gain" : [ 26 ],
					"poly~.6::MLE.dist::LPF_freq" : [ 190.0 ],
					"poly~.6::MLE.dist::LPF_gain" : [ 1.152208752109341 ],
					"poly~.6::MLE.dist::MIX" : [ 127 ],
					"poly~.6::MLE.dist::PHPF_freq" : [ 880.0 ],
					"poly~.6::MLE.dist::PHPF_gain" : [ 0.9208984375 ],
					"poly~.6::MLE.dist::bias" : [ 23 ],
					"poly~.6::MLE.dist::dynamics" : [ 127 ],
					"poly~.6::MLE.dist::tone" : [ 46 ],
					"poly~.6::MLE.dist::volume" : [ 24 ],
					"poly~.7::MLE.seq::enable" : [ 3, 8, 1, 0, 8, 0, 1000, 2000, 3000, 4000, 5000, 6000, 7000, 2, 2, 2, 2, 2, 2, 2, 2 ],
					"poly~.7::MLE.seq::hitProb" : [ 127, 127, 127, 127, 127, 127, 127, 127 ],
					"poly~.7::MLE.seq::seq" : [ 7, 0, 0, 0, 0, 0, 0, 0 ],
					"poly~.7::MLE.dist::FB1gain" : [ 0 ],
					"poly~.7::MLE.dist::FB2_gain" : [ 63 ],
					"poly~.7::MLE.dist::FB2samples" : [ 30 ],
					"poly~.7::MLE.dist::Gain" : [ 26 ],
					"poly~.7::MLE.dist::LPF_freq" : [ 190.0 ],
					"poly~.7::MLE.dist::LPF_gain" : [ 1.152208752109341 ],
					"poly~.7::MLE.dist::MIX" : [ 127 ],
					"poly~.7::MLE.dist::PHPF_freq" : [ 880.0 ],
					"poly~.7::MLE.dist::PHPF_gain" : [ 0.9208984375 ],
					"poly~.7::MLE.dist::bias" : [ 23 ],
					"poly~.7::MLE.dist::dynamics" : [ 127 ],
					"poly~.7::MLE.dist::tone" : [ 46 ],
					"poly~.7::MLE.dist::volume" : [ 24 ],
					"poly~.8::MLE.seq::enable" : [ 3, 8, 1, 0, 8, 0, 1000, 2000, 3000, 4000, 5000, 6000, 7000, 2, 2, 2, 2, 2, 2, 2, 2 ],
					"poly~.8::MLE.seq::hitProb" : [ 127, 127, 127, 127, 127, 127, 127, 127 ],
					"poly~.8::MLE.seq::seq" : [ 7, 0, 0, 0, 0, 0, 0, 0 ],
					"poly~.8::MLE.dist::FB1gain" : [ 0 ],
					"poly~.8::MLE.dist::FB2_gain" : [ 63 ],
					"poly~.8::MLE.dist::FB2samples" : [ 30 ],
					"poly~.8::MLE.dist::Gain" : [ 26 ],
					"poly~.8::MLE.dist::LPF_freq" : [ 190.0 ],
					"poly~.8::MLE.dist::LPF_gain" : [ 1.152208752109341 ],
					"poly~.8::MLE.dist::MIX" : [ 127 ],
					"poly~.8::MLE.dist::PHPF_freq" : [ 880.0 ],
					"poly~.8::MLE.dist::PHPF_gain" : [ 0.9208984375 ],
					"poly~.8::MLE.dist::bias" : [ 23 ],
					"poly~.8::MLE.dist::dynamics" : [ 127 ],
					"poly~.8::MLE.dist::tone" : [ 46 ],
					"poly~.8::MLE.dist::volume" : [ 24 ],
					"MLE.seq[1]::enable" : [ 3, 8, 1, 0, 8, 0, 1000, 2000, 3000, 4000, 5000, 6000, 7000, 2, 2, 2, 2, 2, 2, 2, 2 ],
					"MLE.seq[1]::hitProb" : [ 127, 127, 127, 127, 127, 127, 127, 127 ],
					"MLE.seq[1]::seq" : [ 4, 4, 4, 4, 3, 2, 1, 1 ],
					"MLE.seq[2]::enable" : [ 3, 8, 1, 0, 8, 0, 1000, 2000, 3000, 4000, 5000, 6000, 7000, 2, 2, 2, 2, 2, 2, 2, 2 ],
					"MLE.seq[2]::hitProb" : [ 127, 127, 127, 127, 127, 127, 127, 127 ],
					"MLE.seq[2]::seq" : [ 6, 6, 6, 5, 4, 3, 1, 0 ],
					"MLE.seq[4]::enable" : [ 3, 8, 1, 0, 8, 0, 1000, 2000, 3000, 4000, 5000, 6000, 7000, 2, 2, 2, 2, 2, 2, 2, 2 ],
					"MLE.seq[4]::hitProb" : [ 127, 127, 127, 127, 127, 127, 127, 127 ],
					"MLE.seq[4]::seq" : [ 7, 0, 0, 0, 0, 0, 0, 0 ],
					"MLE.seq[3]::enable" : [ 3, 8, 1, 0, 8, 0, 1000, 2000, 3000, 4000, 5000, 6000, 7000, 2, 2, 2, 2, 2, 2, 2, 2 ],
					"MLE.seq[3]::hitProb" : [ 127, 127, 127, 127, 127, 127, 127, 127 ],
					"MLE.seq[3]::seq" : [ 7, 0, 0, 0, 0, 0, 0, 0 ],
					"MLE.seq[8]::enable" : [ 3, 8, 1, 0, 8, 0, 1000, 2000, 3000, 4000, 5000, 6000, 7000, 2, 2, 2, 2, 2, 2, 2, 2 ],
					"MLE.seq[8]::hitProb" : [ 127, 127, 127, 127, 127, 127, 127, 127 ],
					"MLE.seq[8]::seq" : [ 6, 7, 7, 6, 6, 6, 5, 0 ],
					"MLE.seq[7]::enable" : [ 3, 8, 1, 0, 8, 0, 1000, 2000, 3000, 4000, 5000, 6000, 7000, 2, 2, 2, 2, 2, 2, 2, 2 ],
					"MLE.seq[7]::hitProb" : [ 127, 127, 127, 127, 127, 127, 127, 127 ],
					"MLE.seq[7]::seq" : [ 7, 0, 0, 6, 6, 6, 6, 6 ],
					"MLE.seq[6]::enable" : [ 3, 8, 1, 0, 8, 0, 1000, 2000, 3000, 4000, 5000, 6000, 7000, 2, 2, 2, 2, 2, 2, 2, 2 ],
					"MLE.seq[6]::hitProb" : [ 127, 127, 127, 127, 127, 127, 127, 127 ],
					"MLE.seq[6]::seq" : [ 7, 0, 0, 0, 0, 0, 0, 0 ],
					"MLE.seq::enable" : [ 3, 8, 1, 0, 8, 0, 1000, 2000, 3000, 4000, 5000, 6000, 7000, 2, 2, 2, 2, 2, 2, 2, 2 ],
					"MLE.seq::hitProb" : [ 127, 127, 127, 127, 127, 127, 127, 127 ],
					"MLE.seq::seq" : [ 6, 6, 6, 5, 4, 3, 1, 0 ]
				}

			}
,
			"10" : 			{
				"id" : 10,
				"name" : "bass",
				"data" : 				{
					"decay" : [ 0.316134375828254 ],
					"filterFreq" : [ 0.327272727272727 ],
					"fuzz" : [ 0.254545454545455 ],
					"noise" : [ 0.0 ],
					"octave" : [ 2 ],
					"panning" : [ 0.50002876620907 ],
					"reverb" : [ 0.310064935064935 ],
					"subdivide" : [ 2 ],
					"poly~.1::MLE.seq::enable" : [ 3, 8, 1, 0, 4, 0, 3000, 5000, 7000, 2, 2, 2, 2, 2, 2, 2, 2 ],
					"poly~.1::MLE.seq::hitProb" : [ 127, 0, 0, 127, 0, 127, 0, 127 ],
					"poly~.1::MLE.seq::seq" : [ 0, 0, 0, 0, 0, 0, 0, 0 ],
					"poly~.1::MLE.dist::FB1gain" : [ 0 ],
					"poly~.1::MLE.dist::FB2_gain" : [ 63 ],
					"poly~.1::MLE.dist::FB2samples" : [ 30 ],
					"poly~.1::MLE.dist::Gain" : [ 37 ],
					"poly~.1::MLE.dist::LPF_freq" : [ 190.0 ],
					"poly~.1::MLE.dist::LPF_gain" : [ 1.152208752109341 ],
					"poly~.1::MLE.dist::MIX" : [ 8 ],
					"poly~.1::MLE.dist::PHPF_freq" : [ 880.0 ],
					"poly~.1::MLE.dist::PHPF_gain" : [ 0.9208984375 ],
					"poly~.1::MLE.dist::bias" : [ 23 ],
					"poly~.1::MLE.dist::dynamics" : [ 127 ],
					"poly~.1::MLE.dist::tone" : [ 46 ],
					"poly~.1::MLE.dist::volume" : [ 94 ],
					"poly~.2::MLE.seq::enable" : [ 3, 8, 1, 0, 8, 0, 1000, 2000, 3000, 4000, 5000, 6000, 7000, 2, 2, 2, 2, 2, 2, 2, 2 ],
					"poly~.2::MLE.seq::hitProb" : [ 127, 127, 127, 127, 127, 127, 127, 127 ],
					"poly~.2::MLE.seq::seq" : [ 7, 0, 0, 0, 0, 0, 0, 0 ],
					"poly~.2::MLE.dist::FB1gain" : [ 0 ],
					"poly~.2::MLE.dist::FB2_gain" : [ 63 ],
					"poly~.2::MLE.dist::FB2samples" : [ 30 ],
					"poly~.2::MLE.dist::Gain" : [ 26 ],
					"poly~.2::MLE.dist::LPF_freq" : [ 190.0 ],
					"poly~.2::MLE.dist::LPF_gain" : [ 1.152208752109341 ],
					"poly~.2::MLE.dist::MIX" : [ 127 ],
					"poly~.2::MLE.dist::PHPF_freq" : [ 880.0 ],
					"poly~.2::MLE.dist::PHPF_gain" : [ 0.9208984375 ],
					"poly~.2::MLE.dist::bias" : [ 23 ],
					"poly~.2::MLE.dist::dynamics" : [ 127 ],
					"poly~.2::MLE.dist::tone" : [ 46 ],
					"poly~.2::MLE.dist::volume" : [ 24 ],
					"poly~.3::MLE.seq::enable" : [ 3, 8, 1, 0, 8, 0, 1000, 2000, 3000, 4000, 5000, 6000, 7000, 2, 2, 2, 2, 2, 2, 2, 2 ],
					"poly~.3::MLE.seq::hitProb" : [ 127, 127, 127, 127, 127, 127, 127, 127 ],
					"poly~.3::MLE.seq::seq" : [ 1, 1, 1, 3, 3, 3, 3, 3 ],
					"poly~.3::MLE.dist::FB1gain" : [ 0 ],
					"poly~.3::MLE.dist::FB2_gain" : [ 63 ],
					"poly~.3::MLE.dist::FB2samples" : [ 30 ],
					"poly~.3::MLE.dist::Gain" : [ 37 ],
					"poly~.3::MLE.dist::LPF_freq" : [ 190.0 ],
					"poly~.3::MLE.dist::LPF_gain" : [ 1.152208752109341 ],
					"poly~.3::MLE.dist::MIX" : [ 8 ],
					"poly~.3::MLE.dist::PHPF_freq" : [ 880.0 ],
					"poly~.3::MLE.dist::PHPF_gain" : [ 0.9208984375 ],
					"poly~.3::MLE.dist::bias" : [ 23 ],
					"poly~.3::MLE.dist::dynamics" : [ 127 ],
					"poly~.3::MLE.dist::tone" : [ 46 ],
					"poly~.3::MLE.dist::volume" : [ 94 ],
					"poly~.4::MLE.seq::enable" : [ 3, 8, 1, 0, 0, 2, 2, 2, 2, 2, 2, 2, 2 ],
					"poly~.4::MLE.seq::hitProb" : [ 0, 0, 0, 0, 0, 0, 0, 0 ],
					"poly~.4::MLE.seq::seq" : [ 2, 2, 2, 2, 2, 2, 2, 2 ],
					"poly~.4::MLE.dist::FB1gain" : [ 0 ],
					"poly~.4::MLE.dist::FB2_gain" : [ 63 ],
					"poly~.4::MLE.dist::FB2samples" : [ 30 ],
					"poly~.4::MLE.dist::Gain" : [ 75 ],
					"poly~.4::MLE.dist::LPF_freq" : [ 190.0 ],
					"poly~.4::MLE.dist::LPF_gain" : [ 1.152208752109341 ],
					"poly~.4::MLE.dist::MIX" : [ 127 ],
					"poly~.4::MLE.dist::PHPF_freq" : [ 880.0 ],
					"poly~.4::MLE.dist::PHPF_gain" : [ 0.9208984375 ],
					"poly~.4::MLE.dist::bias" : [ 23 ],
					"poly~.4::MLE.dist::dynamics" : [ 127 ],
					"poly~.4::MLE.dist::tone" : [ 46 ],
					"poly~.4::MLE.dist::volume" : [ 78 ],
					"poly~.5::MLE.seq::enable" : [ 3, 8, 1, 0, 8, 0, 1000, 2000, 3000, 4000, 5000, 6000, 7000, 2, 2, 2, 2, 2, 2, 2, 2 ],
					"poly~.5::MLE.seq::hitProb" : [ 127, 127, 127, 127, 127, 127, 127, 127 ],
					"poly~.5::MLE.seq::seq" : [ 7, 0, 0, 0, 0, 0, 0, 0 ],
					"poly~.5::MLE.dist::FB1gain" : [ 0 ],
					"poly~.5::MLE.dist::FB2_gain" : [ 63 ],
					"poly~.5::MLE.dist::FB2samples" : [ 30 ],
					"poly~.5::MLE.dist::Gain" : [ 26 ],
					"poly~.5::MLE.dist::LPF_freq" : [ 190.0 ],
					"poly~.5::MLE.dist::LPF_gain" : [ 1.152208752109341 ],
					"poly~.5::MLE.dist::MIX" : [ 127 ],
					"poly~.5::MLE.dist::PHPF_freq" : [ 880.0 ],
					"poly~.5::MLE.dist::PHPF_gain" : [ 0.9208984375 ],
					"poly~.5::MLE.dist::bias" : [ 23 ],
					"poly~.5::MLE.dist::dynamics" : [ 127 ],
					"poly~.5::MLE.dist::tone" : [ 46 ],
					"poly~.5::MLE.dist::volume" : [ 24 ],
					"poly~.6::MLE.seq::enable" : [ 3, 8, 1, 0, 8, 0, 1000, 2000, 3000, 4000, 5000, 6000, 7000, 2, 2, 2, 2, 2, 2, 2, 2 ],
					"poly~.6::MLE.seq::hitProb" : [ 127, 127, 127, 127, 127, 127, 127, 127 ],
					"poly~.6::MLE.seq::seq" : [ 5, 5, 1, 2, 3, 3, 2, 6 ],
					"poly~.6::MLE.dist::FB1gain" : [ 0 ],
					"poly~.6::MLE.dist::FB2_gain" : [ 63 ],
					"poly~.6::MLE.dist::FB2samples" : [ 30 ],
					"poly~.6::MLE.dist::Gain" : [ 37 ],
					"poly~.6::MLE.dist::LPF_freq" : [ 190.0 ],
					"poly~.6::MLE.dist::LPF_gain" : [ 1.152208752109341 ],
					"poly~.6::MLE.dist::MIX" : [ 8 ],
					"poly~.6::MLE.dist::PHPF_freq" : [ 880.0 ],
					"poly~.6::MLE.dist::PHPF_gain" : [ 0.9208984375 ],
					"poly~.6::MLE.dist::bias" : [ 23 ],
					"poly~.6::MLE.dist::dynamics" : [ 127 ],
					"poly~.6::MLE.dist::tone" : [ 46 ],
					"poly~.6::MLE.dist::volume" : [ 94 ],
					"poly~.7::MLE.seq::enable" : [ 3, 8, 1, 0, 8, 0, 1000, 2000, 3000, 4000, 5000, 6000, 7000, 2, 2, 2, 2, 2, 2, 2, 2 ],
					"poly~.7::MLE.seq::hitProb" : [ 127, 127, 127, 127, 127, 127, 127, 127 ],
					"poly~.7::MLE.seq::seq" : [ 2, 3, 2, 3, 2, 3, 2, 3 ],
					"poly~.7::MLE.dist::FB1gain" : [ 0 ],
					"poly~.7::MLE.dist::FB2_gain" : [ 63 ],
					"poly~.7::MLE.dist::FB2samples" : [ 30 ],
					"poly~.7::MLE.dist::Gain" : [ 37 ],
					"poly~.7::MLE.dist::LPF_freq" : [ 190.0 ],
					"poly~.7::MLE.dist::LPF_gain" : [ 1.152208752109341 ],
					"poly~.7::MLE.dist::MIX" : [ 8 ],
					"poly~.7::MLE.dist::PHPF_freq" : [ 880.0 ],
					"poly~.7::MLE.dist::PHPF_gain" : [ 0.9208984375 ],
					"poly~.7::MLE.dist::bias" : [ 23 ],
					"poly~.7::MLE.dist::dynamics" : [ 127 ],
					"poly~.7::MLE.dist::tone" : [ 46 ],
					"poly~.7::MLE.dist::volume" : [ 94 ],
					"poly~.8::MLE.seq::enable" : [ 3, 8, 1, 0, 8, 0, 1000, 2000, 3000, 4000, 5000, 6000, 7000, 2, 2, 2, 2, 2, 2, 2, 2 ],
					"poly~.8::MLE.seq::hitProb" : [ 127, 127, 127, 127, 127, 127, 127, 127 ],
					"poly~.8::MLE.seq::seq" : [ 7, 0, 0, 0, 0, 0, 0, 0 ],
					"poly~.8::MLE.dist::FB1gain" : [ 0 ],
					"poly~.8::MLE.dist::FB2_gain" : [ 63 ],
					"poly~.8::MLE.dist::FB2samples" : [ 30 ],
					"poly~.8::MLE.dist::Gain" : [ 26 ],
					"poly~.8::MLE.dist::LPF_freq" : [ 190.0 ],
					"poly~.8::MLE.dist::LPF_gain" : [ 1.152208752109341 ],
					"poly~.8::MLE.dist::MIX" : [ 127 ],
					"poly~.8::MLE.dist::PHPF_freq" : [ 880.0 ],
					"poly~.8::MLE.dist::PHPF_gain" : [ 0.9208984375 ],
					"poly~.8::MLE.dist::bias" : [ 23 ],
					"poly~.8::MLE.dist::dynamics" : [ 127 ],
					"poly~.8::MLE.dist::tone" : [ 46 ],
					"poly~.8::MLE.dist::volume" : [ 24 ],
					"MLE.seq[1]::enable" : [ 3, 8, 1, 0, 8, 0, 1000, 2000, 3000, 4000, 5000, 6000, 7000, 2, 2, 2, 2, 2, 2, 2, 2 ],
					"MLE.seq[1]::hitProb" : [ 127, 127, 127, 127, 127, 127, 127, 127 ],
					"MLE.seq[1]::seq" : [ 7, 0, 0, 0, 0, 0, 0, 0 ],
					"MLE.seq[2]::enable" : [ 3, 8, 1, 0, 4, 0, 3000, 5000, 7000, 2, 2, 2, 2, 2, 2, 2, 2 ],
					"MLE.seq[2]::hitProb" : [ 127, 0, 0, 127, 0, 127, 0, 127 ],
					"MLE.seq[2]::seq" : [ 0, 0, 0, 0, 0, 0, 0, 0 ],
					"MLE.seq[4]::enable" : [ 3, 8, 1, 0, 8, 0, 1000, 2000, 3000, 4000, 5000, 6000, 7000, 2, 2, 2, 2, 2, 2, 2, 2 ],
					"MLE.seq[4]::hitProb" : [ 127, 127, 127, 127, 127, 127, 127, 127 ],
					"MLE.seq[4]::seq" : [ 5, 5, 1, 2, 3, 3, 2, 6 ],
					"MLE.seq[3]::enable" : [ 3, 8, 1, 0, 8, 0, 1000, 2000, 3000, 4000, 5000, 6000, 7000, 2, 2, 2, 2, 2, 2, 2, 2 ],
					"MLE.seq[3]::hitProb" : [ 127, 127, 127, 127, 127, 127, 127, 127 ],
					"MLE.seq[3]::seq" : [ 1, 1, 1, 3, 3, 3, 3, 3 ],
					"MLE.seq[8]::enable" : [ 3, 8, 1, 0, 0, 2, 2, 2, 2, 2, 2, 2, 2 ],
					"MLE.seq[8]::hitProb" : [ 0, 0, 0, 0, 0, 0, 0, 0 ],
					"MLE.seq[8]::seq" : [ 2, 2, 2, 2, 2, 2, 2, 2 ],
					"MLE.seq[7]::enable" : [ 3, 8, 1, 0, 8, 0, 1000, 2000, 3000, 4000, 5000, 6000, 7000, 2, 2, 2, 2, 2, 2, 2, 2 ],
					"MLE.seq[7]::hitProb" : [ 127, 127, 127, 127, 127, 127, 127, 127 ],
					"MLE.seq[7]::seq" : [ 2, 3, 2, 3, 2, 3, 2, 3 ],
					"MLE.seq[6]::enable" : [ 3, 8, 1, 0, 8, 0, 1000, 2000, 3000, 4000, 5000, 6000, 7000, 2, 2, 2, 2, 2, 2, 2, 2 ],
					"MLE.seq[6]::hitProb" : [ 127, 127, 127, 127, 127, 127, 127, 127 ],
					"MLE.seq[6]::seq" : [ 7, 0, 0, 0, 0, 0, 0, 0 ],
					"MLE.seq::enable" : [ 3, 8, 1, 0, 4, 0, 3000, 5000, 7000, 2, 2, 2, 2, 2, 2, 2, 2 ],
					"MLE.seq::hitProb" : [ 127, 0, 0, 127, 0, 127, 0, 127 ],
					"MLE.seq::seq" : [ 0, 0, 0, 0, 0, 0, 0, 0 ]
				}

			}
,
			"11" : 			{
				"id" : 11,
				"name" : "hihat",
				"data" : 				{
					"decay" : [ 0.145454545454545 ],
					"filterFreq" : [ 1.0 ],
					"fuzz" : [ 1.0 ],
					"noise" : [ 1.0 ],
					"octave" : [ 2 ],
					"panning" : [ 0.50002876620907 ],
					"reverb" : [ 0.290909090909091 ],
					"subdivide" : [ 2 ],
					"poly~.1::MLE.seq::enable" : [ 3, 8, 1, 0, 4, 0, 3000, 5000, 7000, 2, 2, 2, 2, 2, 2, 2, 2 ],
					"poly~.1::MLE.seq::hitProb" : [ 127, 0, 0, 127, 0, 127, 0, 127 ],
					"poly~.1::MLE.seq::seq" : [ 0, 0, 0, 0, 0, 0, 0, 0 ],
					"poly~.1::MLE.dist::FB1gain" : [ 0 ],
					"poly~.1::MLE.dist::FB2_gain" : [ 63 ],
					"poly~.1::MLE.dist::FB2samples" : [ 30 ],
					"poly~.1::MLE.dist::Gain" : [ 75 ],
					"poly~.1::MLE.dist::LPF_freq" : [ 190.0 ],
					"poly~.1::MLE.dist::LPF_gain" : [ 1.152208752109341 ],
					"poly~.1::MLE.dist::MIX" : [ 127 ],
					"poly~.1::MLE.dist::PHPF_freq" : [ 880.0 ],
					"poly~.1::MLE.dist::PHPF_gain" : [ 0.9208984375 ],
					"poly~.1::MLE.dist::bias" : [ 23 ],
					"poly~.1::MLE.dist::dynamics" : [ 127 ],
					"poly~.1::MLE.dist::tone" : [ 46 ],
					"poly~.1::MLE.dist::volume" : [ 78 ],
					"poly~.2::MLE.seq::enable" : [ 3, 8, 1, 0, 8, 0, 1000, 2000, 3000, 4000, 5000, 6000, 7000, 2, 2, 2, 2, 2, 2, 2, 2 ],
					"poly~.2::MLE.seq::hitProb" : [ 127, 127, 127, 127, 127, 127, 127, 127 ],
					"poly~.2::MLE.seq::seq" : [ 7, 0, 0, 0, 0, 0, 0, 0 ],
					"poly~.2::MLE.dist::FB1gain" : [ 0 ],
					"poly~.2::MLE.dist::FB2_gain" : [ 63 ],
					"poly~.2::MLE.dist::FB2samples" : [ 30 ],
					"poly~.2::MLE.dist::Gain" : [ 26 ],
					"poly~.2::MLE.dist::LPF_freq" : [ 190.0 ],
					"poly~.2::MLE.dist::LPF_gain" : [ 1.152208752109341 ],
					"poly~.2::MLE.dist::MIX" : [ 127 ],
					"poly~.2::MLE.dist::PHPF_freq" : [ 880.0 ],
					"poly~.2::MLE.dist::PHPF_gain" : [ 0.9208984375 ],
					"poly~.2::MLE.dist::bias" : [ 23 ],
					"poly~.2::MLE.dist::dynamics" : [ 127 ],
					"poly~.2::MLE.dist::tone" : [ 46 ],
					"poly~.2::MLE.dist::volume" : [ 24 ],
					"poly~.3::MLE.seq::enable" : [ 3, 8, 1, 0, 8, 0, 1000, 2000, 3000, 4000, 5000, 6000, 7000, 2, 2, 2, 2, 2, 2, 2, 2 ],
					"poly~.3::MLE.seq::hitProb" : [ 127, 127, 127, 127, 127, 127, 127, 127 ],
					"poly~.3::MLE.seq::seq" : [ 1, 1, 1, 3, 3, 3, 3, 3 ],
					"poly~.3::MLE.dist::FB1gain" : [ 0 ],
					"poly~.3::MLE.dist::FB2_gain" : [ 63 ],
					"poly~.3::MLE.dist::FB2samples" : [ 30 ],
					"poly~.3::MLE.dist::Gain" : [ 37 ],
					"poly~.3::MLE.dist::LPF_freq" : [ 190.0 ],
					"poly~.3::MLE.dist::LPF_gain" : [ 1.152208752109341 ],
					"poly~.3::MLE.dist::MIX" : [ 8 ],
					"poly~.3::MLE.dist::PHPF_freq" : [ 880.0 ],
					"poly~.3::MLE.dist::PHPF_gain" : [ 0.9208984375 ],
					"poly~.3::MLE.dist::bias" : [ 23 ],
					"poly~.3::MLE.dist::dynamics" : [ 127 ],
					"poly~.3::MLE.dist::tone" : [ 46 ],
					"poly~.3::MLE.dist::volume" : [ 94 ],
					"poly~.4::MLE.seq::enable" : [ 3, 8, 1, 0, 0, 2, 2, 2, 2, 2, 2, 2, 2 ],
					"poly~.4::MLE.seq::hitProb" : [ 0, 0, 0, 0, 0, 0, 0, 0 ],
					"poly~.4::MLE.seq::seq" : [ 2, 2, 2, 2, 2, 2, 2, 2 ],
					"poly~.4::MLE.dist::FB1gain" : [ 0 ],
					"poly~.4::MLE.dist::FB2_gain" : [ 63 ],
					"poly~.4::MLE.dist::FB2samples" : [ 30 ],
					"poly~.4::MLE.dist::Gain" : [ 75 ],
					"poly~.4::MLE.dist::LPF_freq" : [ 190.0 ],
					"poly~.4::MLE.dist::LPF_gain" : [ 1.152208752109341 ],
					"poly~.4::MLE.dist::MIX" : [ 127 ],
					"poly~.4::MLE.dist::PHPF_freq" : [ 880.0 ],
					"poly~.4::MLE.dist::PHPF_gain" : [ 0.9208984375 ],
					"poly~.4::MLE.dist::bias" : [ 23 ],
					"poly~.4::MLE.dist::dynamics" : [ 127 ],
					"poly~.4::MLE.dist::tone" : [ 46 ],
					"poly~.4::MLE.dist::volume" : [ 78 ],
					"poly~.5::MLE.seq::enable" : [ 3, 8, 1, 0, 8, 0, 1000, 2000, 3000, 4000, 5000, 6000, 7000, 2, 2, 2, 2, 2, 2, 2, 2 ],
					"poly~.5::MLE.seq::hitProb" : [ 127, 127, 127, 127, 127, 127, 127, 127 ],
					"poly~.5::MLE.seq::seq" : [ 7, 0, 0, 0, 0, 0, 0, 0 ],
					"poly~.5::MLE.dist::FB1gain" : [ 0 ],
					"poly~.5::MLE.dist::FB2_gain" : [ 63 ],
					"poly~.5::MLE.dist::FB2samples" : [ 30 ],
					"poly~.5::MLE.dist::Gain" : [ 26 ],
					"poly~.5::MLE.dist::LPF_freq" : [ 190.0 ],
					"poly~.5::MLE.dist::LPF_gain" : [ 1.152208752109341 ],
					"poly~.5::MLE.dist::MIX" : [ 127 ],
					"poly~.5::MLE.dist::PHPF_freq" : [ 880.0 ],
					"poly~.5::MLE.dist::PHPF_gain" : [ 0.9208984375 ],
					"poly~.5::MLE.dist::bias" : [ 23 ],
					"poly~.5::MLE.dist::dynamics" : [ 127 ],
					"poly~.5::MLE.dist::tone" : [ 46 ],
					"poly~.5::MLE.dist::volume" : [ 24 ],
					"poly~.6::MLE.seq::enable" : [ 3, 8, 1, 0, 8, 0, 1000, 2000, 3000, 4000, 5000, 6000, 7000, 2, 2, 2, 2, 2, 2, 2, 2 ],
					"poly~.6::MLE.seq::hitProb" : [ 127, 127, 127, 127, 127, 127, 127, 127 ],
					"poly~.6::MLE.seq::seq" : [ 5, 5, 1, 2, 3, 3, 2, 6 ],
					"poly~.6::MLE.dist::FB1gain" : [ 0 ],
					"poly~.6::MLE.dist::FB2_gain" : [ 63 ],
					"poly~.6::MLE.dist::FB2samples" : [ 30 ],
					"poly~.6::MLE.dist::Gain" : [ 40 ],
					"poly~.6::MLE.dist::LPF_freq" : [ 190.0 ],
					"poly~.6::MLE.dist::LPF_gain" : [ 1.152208752109341 ],
					"poly~.6::MLE.dist::MIX" : [ 12 ],
					"poly~.6::MLE.dist::PHPF_freq" : [ 880.0 ],
					"poly~.6::MLE.dist::PHPF_gain" : [ 0.9208984375 ],
					"poly~.6::MLE.dist::bias" : [ 23 ],
					"poly~.6::MLE.dist::dynamics" : [ 127 ],
					"poly~.6::MLE.dist::tone" : [ 46 ],
					"poly~.6::MLE.dist::volume" : [ 93 ],
					"poly~.7::MLE.seq::enable" : [ 3, 8, 1, 0, 8, 0, 1000, 2000, 3000, 4000, 5000, 6000, 7000, 2, 2, 2, 2, 2, 2, 2, 2 ],
					"poly~.7::MLE.seq::hitProb" : [ 127, 127, 127, 127, 127, 127, 127, 127 ],
					"poly~.7::MLE.seq::seq" : [ 2, 3, 2, 3, 2, 3, 2, 3 ],
					"poly~.7::MLE.dist::FB1gain" : [ 0 ],
					"poly~.7::MLE.dist::FB2_gain" : [ 63 ],
					"poly~.7::MLE.dist::FB2samples" : [ 30 ],
					"poly~.7::MLE.dist::Gain" : [ 37 ],
					"poly~.7::MLE.dist::LPF_freq" : [ 190.0 ],
					"poly~.7::MLE.dist::LPF_gain" : [ 1.152208752109341 ],
					"poly~.7::MLE.dist::MIX" : [ 8 ],
					"poly~.7::MLE.dist::PHPF_freq" : [ 880.0 ],
					"poly~.7::MLE.dist::PHPF_gain" : [ 0.9208984375 ],
					"poly~.7::MLE.dist::bias" : [ 23 ],
					"poly~.7::MLE.dist::dynamics" : [ 127 ],
					"poly~.7::MLE.dist::tone" : [ 46 ],
					"poly~.7::MLE.dist::volume" : [ 94 ],
					"poly~.8::MLE.seq::enable" : [ 3, 8, 1, 0, 8, 0, 1000, 2000, 3000, 4000, 5000, 6000, 7000, 2, 2, 2, 2, 2, 2, 2, 2 ],
					"poly~.8::MLE.seq::hitProb" : [ 127, 127, 127, 127, 127, 127, 127, 127 ],
					"poly~.8::MLE.seq::seq" : [ 7, 0, 0, 0, 0, 0, 0, 0 ],
					"poly~.8::MLE.dist::FB1gain" : [ 0 ],
					"poly~.8::MLE.dist::FB2_gain" : [ 63 ],
					"poly~.8::MLE.dist::FB2samples" : [ 30 ],
					"poly~.8::MLE.dist::Gain" : [ 26 ],
					"poly~.8::MLE.dist::LPF_freq" : [ 190.0 ],
					"poly~.8::MLE.dist::LPF_gain" : [ 1.152208752109341 ],
					"poly~.8::MLE.dist::MIX" : [ 127 ],
					"poly~.8::MLE.dist::PHPF_freq" : [ 880.0 ],
					"poly~.8::MLE.dist::PHPF_gain" : [ 0.9208984375 ],
					"poly~.8::MLE.dist::bias" : [ 23 ],
					"poly~.8::MLE.dist::dynamics" : [ 127 ],
					"poly~.8::MLE.dist::tone" : [ 46 ],
					"poly~.8::MLE.dist::volume" : [ 24 ],
					"MLE.seq[1]::enable" : [ 3, 8, 1, 0, 8, 0, 1000, 2000, 3000, 4000, 5000, 6000, 7000, 2, 2, 2, 2, 2, 2, 2, 2 ],
					"MLE.seq[1]::hitProb" : [ 127, 127, 127, 127, 127, 127, 127, 127 ],
					"MLE.seq[1]::seq" : [ 7, 0, 0, 0, 0, 0, 0, 0 ],
					"MLE.seq[2]::enable" : [ 3, 8, 1, 0, 4, 0, 3000, 5000, 7000, 2, 2, 2, 2, 2, 2, 2, 2 ],
					"MLE.seq[2]::hitProb" : [ 127, 0, 0, 127, 0, 127, 0, 127 ],
					"MLE.seq[2]::seq" : [ 0, 0, 0, 0, 0, 0, 0, 0 ],
					"MLE.seq[4]::enable" : [ 3, 8, 1, 0, 8, 0, 1000, 2000, 3000, 4000, 5000, 6000, 7000, 2, 2, 2, 2, 2, 2, 2, 2 ],
					"MLE.seq[4]::hitProb" : [ 127, 127, 127, 127, 127, 127, 127, 127 ],
					"MLE.seq[4]::seq" : [ 5, 5, 1, 2, 3, 3, 2, 6 ],
					"MLE.seq[3]::enable" : [ 3, 8, 1, 0, 8, 0, 1000, 2000, 3000, 4000, 5000, 6000, 7000, 2, 2, 2, 2, 2, 2, 2, 2 ],
					"MLE.seq[3]::hitProb" : [ 127, 127, 127, 127, 127, 127, 127, 127 ],
					"MLE.seq[3]::seq" : [ 1, 1, 1, 3, 3, 3, 3, 3 ],
					"MLE.seq[8]::enable" : [ 3, 8, 1, 0, 0, 2, 2, 2, 2, 2, 2, 2, 2 ],
					"MLE.seq[8]::hitProb" : [ 0, 0, 0, 0, 0, 0, 0, 0 ],
					"MLE.seq[8]::seq" : [ 2, 2, 2, 2, 2, 2, 2, 2 ],
					"MLE.seq[7]::enable" : [ 3, 8, 1, 0, 8, 0, 1000, 2000, 3000, 4000, 5000, 6000, 7000, 2, 2, 2, 2, 2, 2, 2, 2 ],
					"MLE.seq[7]::hitProb" : [ 127, 127, 127, 127, 127, 127, 127, 127 ],
					"MLE.seq[7]::seq" : [ 2, 3, 2, 3, 2, 3, 2, 3 ],
					"MLE.seq[6]::enable" : [ 3, 8, 1, 0, 8, 0, 1000, 2000, 3000, 4000, 5000, 6000, 7000, 2, 2, 2, 2, 2, 2, 2, 2 ],
					"MLE.seq[6]::hitProb" : [ 127, 127, 127, 127, 127, 127, 127, 127 ],
					"MLE.seq[6]::seq" : [ 7, 0, 0, 0, 0, 0, 0, 0 ],
					"MLE.seq::enable" : [ 3, 8, 1, 0, 4, 0, 3000, 5000, 7000, 2, 2, 2, 2, 2, 2, 2, 2 ],
					"MLE.seq::hitProb" : [ 127, 0, 0, 127, 0, 127, 0, 127 ],
					"MLE.seq::seq" : [ 0, 0, 0, 0, 0, 0, 0, 0 ]
				}

			}
,
			"12" : 			{
				"id" : 12,
				"name" : "drum",
				"data" : 				{
					"decay" : [ 0.145454545454545 ],
					"filterFreq" : [ 0.272727272727273 ],
					"fuzz" : [ 0.254545454545455 ],
					"noise" : [ 1.0 ],
					"octave" : [ 2 ],
					"panning" : [ 0.50002876620907 ],
					"reverb" : [ 0.418181818181818 ],
					"subdivide" : [ 2 ],
					"poly~.1::MLE.seq::enable" : [ 3, 8, 1, 0, 4, 0, 3000, 5000, 7000, 2, 2, 2, 2, 2, 2, 2, 2 ],
					"poly~.1::MLE.seq::hitProb" : [ 127, 0, 0, 127, 0, 127, 0, 127 ],
					"poly~.1::MLE.seq::seq" : [ 0, 0, 0, 0, 0, 0, 0, 0 ],
					"poly~.1::MLE.dist::FB1gain" : [ 0 ],
					"poly~.1::MLE.dist::FB2_gain" : [ 63 ],
					"poly~.1::MLE.dist::FB2samples" : [ 30 ],
					"poly~.1::MLE.dist::Gain" : [ 37 ],
					"poly~.1::MLE.dist::LPF_freq" : [ 190.0 ],
					"poly~.1::MLE.dist::LPF_gain" : [ 1.152208752109341 ],
					"poly~.1::MLE.dist::MIX" : [ 8 ],
					"poly~.1::MLE.dist::PHPF_freq" : [ 880.0 ],
					"poly~.1::MLE.dist::PHPF_gain" : [ 0.9208984375 ],
					"poly~.1::MLE.dist::bias" : [ 23 ],
					"poly~.1::MLE.dist::dynamics" : [ 127 ],
					"poly~.1::MLE.dist::tone" : [ 46 ],
					"poly~.1::MLE.dist::volume" : [ 94 ],
					"poly~.2::MLE.seq::enable" : [ 3, 8, 1, 0, 8, 0, 1000, 2000, 3000, 4000, 5000, 6000, 7000, 2, 2, 2, 2, 2, 2, 2, 2 ],
					"poly~.2::MLE.seq::hitProb" : [ 127, 127, 127, 127, 127, 127, 127, 127 ],
					"poly~.2::MLE.seq::seq" : [ 7, 0, 0, 0, 0, 0, 0, 0 ],
					"poly~.2::MLE.dist::FB1gain" : [ 0 ],
					"poly~.2::MLE.dist::FB2_gain" : [ 63 ],
					"poly~.2::MLE.dist::FB2samples" : [ 30 ],
					"poly~.2::MLE.dist::Gain" : [ 26 ],
					"poly~.2::MLE.dist::LPF_freq" : [ 190.0 ],
					"poly~.2::MLE.dist::LPF_gain" : [ 1.152208752109341 ],
					"poly~.2::MLE.dist::MIX" : [ 127 ],
					"poly~.2::MLE.dist::PHPF_freq" : [ 880.0 ],
					"poly~.2::MLE.dist::PHPF_gain" : [ 0.9208984375 ],
					"poly~.2::MLE.dist::bias" : [ 23 ],
					"poly~.2::MLE.dist::dynamics" : [ 127 ],
					"poly~.2::MLE.dist::tone" : [ 46 ],
					"poly~.2::MLE.dist::volume" : [ 24 ],
					"poly~.3::MLE.seq::enable" : [ 3, 8, 1, 0, 8, 0, 1000, 2000, 3000, 4000, 5000, 6000, 7000, 2, 2, 2, 2, 2, 2, 2, 2 ],
					"poly~.3::MLE.seq::hitProb" : [ 127, 127, 127, 127, 127, 127, 127, 127 ],
					"poly~.3::MLE.seq::seq" : [ 1, 1, 1, 3, 3, 3, 3, 3 ],
					"poly~.3::MLE.dist::FB1gain" : [ 0 ],
					"poly~.3::MLE.dist::FB2_gain" : [ 63 ],
					"poly~.3::MLE.dist::FB2samples" : [ 30 ],
					"poly~.3::MLE.dist::Gain" : [ 37 ],
					"poly~.3::MLE.dist::LPF_freq" : [ 190.0 ],
					"poly~.3::MLE.dist::LPF_gain" : [ 1.152208752109341 ],
					"poly~.3::MLE.dist::MIX" : [ 8 ],
					"poly~.3::MLE.dist::PHPF_freq" : [ 880.0 ],
					"poly~.3::MLE.dist::PHPF_gain" : [ 0.9208984375 ],
					"poly~.3::MLE.dist::bias" : [ 23 ],
					"poly~.3::MLE.dist::dynamics" : [ 127 ],
					"poly~.3::MLE.dist::tone" : [ 46 ],
					"poly~.3::MLE.dist::volume" : [ 94 ],
					"poly~.4::MLE.seq::enable" : [ 3, 8, 1, 0, 0, 2, 2, 2, 2, 2, 2, 2, 2 ],
					"poly~.4::MLE.seq::hitProb" : [ 0, 0, 0, 0, 0, 0, 0, 0 ],
					"poly~.4::MLE.seq::seq" : [ 2, 2, 2, 2, 2, 2, 2, 2 ],
					"poly~.4::MLE.dist::FB1gain" : [ 0 ],
					"poly~.4::MLE.dist::FB2_gain" : [ 63 ],
					"poly~.4::MLE.dist::FB2samples" : [ 30 ],
					"poly~.4::MLE.dist::Gain" : [ 75 ],
					"poly~.4::MLE.dist::LPF_freq" : [ 190.0 ],
					"poly~.4::MLE.dist::LPF_gain" : [ 1.152208752109341 ],
					"poly~.4::MLE.dist::MIX" : [ 127 ],
					"poly~.4::MLE.dist::PHPF_freq" : [ 880.0 ],
					"poly~.4::MLE.dist::PHPF_gain" : [ 0.9208984375 ],
					"poly~.4::MLE.dist::bias" : [ 23 ],
					"poly~.4::MLE.dist::dynamics" : [ 127 ],
					"poly~.4::MLE.dist::tone" : [ 46 ],
					"poly~.4::MLE.dist::volume" : [ 78 ],
					"poly~.5::MLE.seq::enable" : [ 3, 8, 1, 0, 8, 0, 1000, 2000, 3000, 4000, 5000, 6000, 7000, 2, 2, 2, 2, 2, 2, 2, 2 ],
					"poly~.5::MLE.seq::hitProb" : [ 127, 127, 127, 127, 127, 127, 127, 127 ],
					"poly~.5::MLE.seq::seq" : [ 7, 0, 0, 0, 0, 0, 0, 0 ],
					"poly~.5::MLE.dist::FB1gain" : [ 0 ],
					"poly~.5::MLE.dist::FB2_gain" : [ 63 ],
					"poly~.5::MLE.dist::FB2samples" : [ 30 ],
					"poly~.5::MLE.dist::Gain" : [ 26 ],
					"poly~.5::MLE.dist::LPF_freq" : [ 190.0 ],
					"poly~.5::MLE.dist::LPF_gain" : [ 1.152208752109341 ],
					"poly~.5::MLE.dist::MIX" : [ 127 ],
					"poly~.5::MLE.dist::PHPF_freq" : [ 880.0 ],
					"poly~.5::MLE.dist::PHPF_gain" : [ 0.9208984375 ],
					"poly~.5::MLE.dist::bias" : [ 23 ],
					"poly~.5::MLE.dist::dynamics" : [ 127 ],
					"poly~.5::MLE.dist::tone" : [ 46 ],
					"poly~.5::MLE.dist::volume" : [ 24 ],
					"poly~.6::MLE.seq::enable" : [ 3, 8, 1, 0, 8, 0, 1000, 2000, 3000, 4000, 5000, 6000, 7000, 2, 2, 2, 2, 2, 2, 2, 2 ],
					"poly~.6::MLE.seq::hitProb" : [ 127, 127, 127, 127, 127, 127, 127, 127 ],
					"poly~.6::MLE.seq::seq" : [ 5, 5, 1, 2, 3, 3, 2, 6 ],
					"poly~.6::MLE.dist::FB1gain" : [ 0 ],
					"poly~.6::MLE.dist::FB2_gain" : [ 63 ],
					"poly~.6::MLE.dist::FB2samples" : [ 30 ],
					"poly~.6::MLE.dist::Gain" : [ 40 ],
					"poly~.6::MLE.dist::LPF_freq" : [ 190.0 ],
					"poly~.6::MLE.dist::LPF_gain" : [ 1.152208752109341 ],
					"poly~.6::MLE.dist::MIX" : [ 12 ],
					"poly~.6::MLE.dist::PHPF_freq" : [ 880.0 ],
					"poly~.6::MLE.dist::PHPF_gain" : [ 0.9208984375 ],
					"poly~.6::MLE.dist::bias" : [ 23 ],
					"poly~.6::MLE.dist::dynamics" : [ 127 ],
					"poly~.6::MLE.dist::tone" : [ 46 ],
					"poly~.6::MLE.dist::volume" : [ 93 ],
					"poly~.7::MLE.seq::enable" : [ 3, 8, 1, 0, 8, 0, 1000, 2000, 3000, 4000, 5000, 6000, 7000, 2, 2, 2, 2, 2, 2, 2, 2 ],
					"poly~.7::MLE.seq::hitProb" : [ 127, 127, 127, 127, 127, 127, 127, 127 ],
					"poly~.7::MLE.seq::seq" : [ 2, 3, 2, 3, 2, 3, 2, 3 ],
					"poly~.7::MLE.dist::FB1gain" : [ 0 ],
					"poly~.7::MLE.dist::FB2_gain" : [ 63 ],
					"poly~.7::MLE.dist::FB2samples" : [ 30 ],
					"poly~.7::MLE.dist::Gain" : [ 37 ],
					"poly~.7::MLE.dist::LPF_freq" : [ 190.0 ],
					"poly~.7::MLE.dist::LPF_gain" : [ 1.152208752109341 ],
					"poly~.7::MLE.dist::MIX" : [ 8 ],
					"poly~.7::MLE.dist::PHPF_freq" : [ 880.0 ],
					"poly~.7::MLE.dist::PHPF_gain" : [ 0.9208984375 ],
					"poly~.7::MLE.dist::bias" : [ 23 ],
					"poly~.7::MLE.dist::dynamics" : [ 127 ],
					"poly~.7::MLE.dist::tone" : [ 46 ],
					"poly~.7::MLE.dist::volume" : [ 94 ],
					"poly~.8::MLE.seq::enable" : [ 3, 8, 1, 0, 8, 0, 1000, 2000, 3000, 4000, 5000, 6000, 7000, 2, 2, 2, 2, 2, 2, 2, 2 ],
					"poly~.8::MLE.seq::hitProb" : [ 127, 127, 127, 127, 127, 127, 127, 127 ],
					"poly~.8::MLE.seq::seq" : [ 7, 0, 0, 0, 0, 0, 0, 0 ],
					"poly~.8::MLE.dist::FB1gain" : [ 0 ],
					"poly~.8::MLE.dist::FB2_gain" : [ 63 ],
					"poly~.8::MLE.dist::FB2samples" : [ 30 ],
					"poly~.8::MLE.dist::Gain" : [ 26 ],
					"poly~.8::MLE.dist::LPF_freq" : [ 190.0 ],
					"poly~.8::MLE.dist::LPF_gain" : [ 1.152208752109341 ],
					"poly~.8::MLE.dist::MIX" : [ 127 ],
					"poly~.8::MLE.dist::PHPF_freq" : [ 880.0 ],
					"poly~.8::MLE.dist::PHPF_gain" : [ 0.9208984375 ],
					"poly~.8::MLE.dist::bias" : [ 23 ],
					"poly~.8::MLE.dist::dynamics" : [ 127 ],
					"poly~.8::MLE.dist::tone" : [ 46 ],
					"poly~.8::MLE.dist::volume" : [ 24 ],
					"MLE.seq[1]::enable" : [ 3, 8, 1, 0, 8, 0, 1000, 2000, 3000, 4000, 5000, 6000, 7000, 2, 2, 2, 2, 2, 2, 2, 2 ],
					"MLE.seq[1]::hitProb" : [ 127, 127, 127, 127, 127, 127, 127, 127 ],
					"MLE.seq[1]::seq" : [ 7, 0, 0, 0, 0, 0, 0, 0 ],
					"MLE.seq[2]::enable" : [ 3, 8, 1, 0, 4, 0, 3000, 5000, 7000, 2, 2, 2, 2, 2, 2, 2, 2 ],
					"MLE.seq[2]::hitProb" : [ 127, 0, 0, 127, 0, 127, 0, 127 ],
					"MLE.seq[2]::seq" : [ 0, 0, 0, 0, 0, 0, 0, 0 ],
					"MLE.seq[4]::enable" : [ 3, 8, 1, 0, 8, 0, 1000, 2000, 3000, 4000, 5000, 6000, 7000, 2, 2, 2, 2, 2, 2, 2, 2 ],
					"MLE.seq[4]::hitProb" : [ 127, 127, 127, 127, 127, 127, 127, 127 ],
					"MLE.seq[4]::seq" : [ 5, 5, 1, 2, 3, 3, 2, 6 ],
					"MLE.seq[3]::enable" : [ 3, 8, 1, 0, 8, 0, 1000, 2000, 3000, 4000, 5000, 6000, 7000, 2, 2, 2, 2, 2, 2, 2, 2 ],
					"MLE.seq[3]::hitProb" : [ 127, 127, 127, 127, 127, 127, 127, 127 ],
					"MLE.seq[3]::seq" : [ 1, 1, 1, 3, 3, 3, 3, 3 ],
					"MLE.seq[8]::enable" : [ 3, 8, 1, 0, 0, 2, 2, 2, 2, 2, 2, 2, 2 ],
					"MLE.seq[8]::hitProb" : [ 0, 0, 0, 0, 0, 0, 0, 0 ],
					"MLE.seq[8]::seq" : [ 2, 2, 2, 2, 2, 2, 2, 2 ],
					"MLE.seq[7]::enable" : [ 3, 8, 1, 0, 8, 0, 1000, 2000, 3000, 4000, 5000, 6000, 7000, 2, 2, 2, 2, 2, 2, 2, 2 ],
					"MLE.seq[7]::hitProb" : [ 127, 127, 127, 127, 127, 127, 127, 127 ],
					"MLE.seq[7]::seq" : [ 2, 3, 2, 3, 2, 3, 2, 3 ],
					"MLE.seq[6]::enable" : [ 3, 8, 1, 0, 8, 0, 1000, 2000, 3000, 4000, 5000, 6000, 7000, 2, 2, 2, 2, 2, 2, 2, 2 ],
					"MLE.seq[6]::hitProb" : [ 127, 127, 127, 127, 127, 127, 127, 127 ],
					"MLE.seq[6]::seq" : [ 7, 0, 0, 0, 0, 0, 0, 0 ],
					"MLE.seq::enable" : [ 3, 8, 1, 0, 4, 0, 3000, 5000, 7000, 2, 2, 2, 2, 2, 2, 2, 2 ],
					"MLE.seq::hitProb" : [ 127, 0, 0, 127, 0, 127, 0, 127 ],
					"MLE.seq::seq" : [ 0, 0, 0, 0, 0, 0, 0, 0 ]
				}

			}

		}

	}

}
